[
  {
    "word": "I",
    "start": 0.035,
    "end": 0.081
  },
  {
    "word": "knocked",
    "start": 0.197,
    "end": 0.499
  },
  {
    "word": "down",
    "start": 0.546,
    "end": 0.778
  },
  {
    "word": "saplings",
    "start": 0.871,
    "end": 1.533
  },
  {
    "word": "-",
    "start": 1.683,
    "end": 1.707
  },
  {
    "word": "young",
    "start": 1.881,
    "end": 2.136
  },
  {
    "word": "trees",
    "start": 2.206,
    "end": 2.601
  },
  {
    "word": "that",
    "start": 2.647,
    "end": 2.763
  },
  {
    "word": "were",
    "start": 2.81,
    "end": 2.926
  },
  {
    "word": "just",
    "start": 2.972,
    "end": 3.193
  },
  {
    "word": "learning",
    "start": 3.274,
    "end": 3.587
  },
  {
    "word": "to",
    "start": 3.646,
    "end": 3.715
  },
  {
    "word": "grow.",
    "start": 3.785,
    "end": 4.307
  },
  {
    "word": "I",
    "start": 4.458,
    "end": 4.528
  },
  {
    "word": "trampled",
    "start": 4.644,
    "end": 5.108
  },
  {
    "word": "flowers",
    "start": 5.166,
    "end": 5.666
  },
  {
    "word": "that",
    "start": 5.712,
    "end": 5.84
  },
  {
    "word": "had",
    "start": 5.875,
    "end": 5.979
  },
  {
    "word": "just",
    "start": 6.037,
    "end": 6.293
  },
  {
    "word": "begun",
    "start": 6.351,
    "end": 6.653
  },
  {
    "word": "to",
    "start": 6.722,
    "end": 6.792
  },
  {
    "word": "bloom.",
    "start": 6.861,
    "end": 7.396
  },
  {
    "word": "I",
    "start": 7.512,
    "end": 7.57
  },
  {
    "word": "frightened",
    "start": 7.721,
    "end": 8.173
  },
  {
    "word": "rabbits",
    "start": 8.243,
    "end": 8.661
  },
  {
    "word": "and",
    "start": 8.707,
    "end": 8.835
  },
  {
    "word": "birds",
    "start": 8.905,
    "end": 9.265
  },
  {
    "word": "and",
    "start": 9.311,
    "end": 9.416
  },
  {
    "word": "even",
    "start": 9.485,
    "end": 9.706
  },
  {
    "word": "other",
    "start": 9.776,
    "end": 9.985
  },
  {
    "word": "moose",
    "start": 10.043,
    "end": 10.344
  },
  {
    "word": "who",
    "start": 10.368,
    "end": 10.472
  },
  {
    "word": "were",
    "start": 10.519,
    "end": 10.658
  },
  {
    "word": "only",
    "start": 10.704,
    "end": 10.925
  },
  {
    "word": "trying",
    "start": 10.983,
    "end": 11.297
  },
  {
    "word": "to",
    "start": 11.355,
    "end": 11.413
  },
  {
    "word": "help.",
    "start": 11.505,
    "end": 11.923
  }
]