[
  {
    "word": "I",
    "start": 0.035,
    "end": 0.081
  },
  {
    "word": "will",
    "start": 0.163,
    "end": 0.325
  },
  {
    "word": "be",
    "start": 0.372,
    "end": 0.453
  },
  {
    "word": "waiting.",
    "start": 0.488,
    "end": 0.998
  },
  {
    "word": "I",
    "start": 1.44,
    "end": 1.509
  },
  {
    "word": "am",
    "start": 1.625,
    "end": 1.753
  },
  {
    "word": "always",
    "start": 1.869,
    "end": 2.543
  },
  {
    "word": "waiting",
    "start": 2.612,
    "end": 2.972
  },
  {
    "word": "-",
    "start": 3.088,
    "end": 3.111
  },
  {
    "word": "for",
    "start": 3.32,
    "end": 3.46
  },
  {
    "word": "the",
    "start": 3.506,
    "end": 3.587
  },
  {
    "word": "children",
    "start": 3.646,
    "end": 4.11
  },
  {
    "word": "who",
    "start": 4.156,
    "end": 4.261
  },
  {
    "word": "are",
    "start": 4.319,
    "end": 4.447
  },
  {
    "word": "learning",
    "start": 4.493,
    "end": 4.841
  },
  {
    "word": "to",
    "start": 4.911,
    "end": 4.981
  },
  {
    "word": "be",
    "start": 5.05,
    "end": 5.155
  },
  {
    "word": "gentle",
    "start": 5.224,
    "end": 5.747
  },
  {
    "word": "giants.",
    "start": 5.817,
    "end": 6.513
  }
]