[
  {
    "word": "Buenas",
    "start": 0.058,
    "end": 0.383
  },
  {
    "word": "noches,",
    "start": 0.476,
    "end": 0.894
  },
  {
    "word": "mi",
    "start": 0.917,
    "end": 0.998
  },
  {
    "word": "amor.",
    "start": 1.045,
    "end": 1.544
  },
  {
    "word": "Feliz",
    "start": 1.927,
    "end": 2.299
  },
  {
    "word": "Navidad.",
    "start": 2.368,
    "end": 3.088
  },
  {
    "word": "The",
    "start": 3.413,
    "end": 3.541
  },
  {
    "word": "train",
    "start": 3.599,
    "end": 3.878
  },
  {
    "word": "will",
    "start": 3.936,
    "end": 4.122
  },
  {
    "word": "always",
    "start": 4.191,
    "end": 4.574
  },
  {
    "word": "wait",
    "start": 4.632,
    "end": 4.83
  },
  {
    "word": "for",
    "start": 4.888,
    "end": 5.027
  },
  {
    "word": "you.",
    "start": 5.108,
    "end": 5.503
  },
  {
    "word": "\\~",
    "start": 6.2,
    "end": 6.56
  },
  {
    "word": "The",
    "start": 6.803,
    "end": 6.943
  },
  {
    "word": "End",
    "start": 7.024,
    "end": 7.372
  },
  {
    "word": "\\~",
    "start": 7.442,
    "end": 7.848
  },
  {
    "word": "Parent",
    "start": 8.29,
    "end": 8.696
  },
  {
    "word": "Guide",
    "start": 8.766,
    "end": 9.137
  }
]