[
  {
    "word": "Outside,",
    "start": 0.035,
    "end": 0.801
  },
  {
    "word": "the",
    "start": 0.929,
    "end": 1.033
  },
  {
    "word": "first",
    "start": 1.115,
    "end": 1.37
  },
  {
    "word": "stars",
    "start": 1.416,
    "end": 1.834
  },
  {
    "word": "were",
    "start": 1.892,
    "end": 2.043
  },
  {
    "word": "appearing.",
    "start": 2.067,
    "end": 2.786
  },
  {
    "word": "Through",
    "start": 3.39,
    "end": 3.669
  },
  {
    "word": "the",
    "start": 3.704,
    "end": 3.773
  },
  {
    "word": "window,",
    "start": 3.82,
    "end": 4.389
  },
  {
    "word": "the",
    "start": 4.505,
    "end": 4.621
  },
  {
    "word": "moon",
    "start": 4.69,
    "end": 4.946
  },
  {
    "word": "was",
    "start": 5.016,
    "end": 5.155
  },
  {
    "word": "beginning",
    "start": 5.224,
    "end": 5.631
  },
  {
    "word": "its",
    "start": 5.689,
    "end": 5.828
  },
  {
    "word": "nightly",
    "start": 5.909,
    "end": 6.293
  },
  {
    "word": "watch",
    "start": 6.362,
    "end": 6.757
  },
  {
    "word": "over",
    "start": 6.873,
    "end": 7.129
  },
  {
    "word": "all",
    "start": 7.187,
    "end": 7.314
  },
  {
    "word": "the",
    "start": 7.372,
    "end": 7.442
  },
  {
    "word": "children",
    "start": 7.5,
    "end": 7.93
  },
  {
    "word": "of",
    "start": 7.976,
    "end": 8.034
  },
  {
    "word": "the",
    "start": 8.092,
    "end": 8.162
  },
  {
    "word": "world--children",
    "start": 8.22,
    "end": 9.485
  },
  {
    "word": "learning",
    "start": 9.578,
    "end": 9.927
  },
  {
    "word": "to",
    "start": 9.985,
    "end": 10.054
  },
  {
    "word": "choose",
    "start": 10.136,
    "end": 10.519
  },
  {
    "word": "their",
    "start": 10.553,
    "end": 10.728
  },
  {
    "word": "words",
    "start": 10.786,
    "end": 11.146
  },
  {
    "word": "like",
    "start": 11.215,
    "end": 11.436
  },
  {
    "word": "instruments,",
    "start": 11.494,
    "end": 12.353
  },
  {
    "word": "learning",
    "start": 12.562,
    "end": 12.922
  },
  {
    "word": "to",
    "start": 12.992,
    "end": 13.05
  },
  {
    "word": "build",
    "start": 13.131,
    "end": 13.502
  },
  {
    "word": "instead",
    "start": 13.584,
    "end": 14.002
  },
  {
    "word": "of",
    "start": 14.048,
    "end": 14.118
  },
  {
    "word": "break,",
    "start": 14.188,
    "end": 14.826
  },
  {
    "word": "learning",
    "start": 15.105,
    "end": 15.488
  },
  {
    "word": "that",
    "start": 15.546,
    "end": 15.674
  },
  {
    "word": "the",
    "start": 15.72,
    "end": 15.79
  },
  {
    "word": "strongest",
    "start": 15.859,
    "end": 16.394
  },
  {
    "word": "superpower",
    "start": 16.44,
    "end": 17.16
  },
  {
    "word": "isn't",
    "start": 17.276,
    "end": 17.589
  },
  {
    "word": "the",
    "start": 17.636,
    "end": 17.729
  },
  {
    "word": "loudest",
    "start": 17.822,
    "end": 18.298
  },
  {
    "word": "voice,",
    "start": 18.367,
    "end": 18.843
  },
  {
    "word": "but",
    "start": 18.901,
    "end": 19.064
  },
  {
    "word": "the",
    "start": 19.11,
    "end": 19.18
  },
  {
    "word": "most",
    "start": 19.261,
    "end": 19.517
  },
  {
    "word": "thoughtful",
    "start": 19.563,
    "end": 20.027
  },
  {
    "word": "one.",
    "start": 20.109,
    "end": 20.445
  }
]