[
  {
    "word": "He",
    "start": 0.151,
    "end": 0.255
  },
  {
    "word": "could",
    "start": 0.313,
    "end": 0.476
  },
  {
    "word": "see",
    "start": 0.522,
    "end": 0.697
  },
  {
    "word": "it",
    "start": 0.743,
    "end": 0.813
  },
  {
    "word": "clearly",
    "start": 0.871,
    "end": 1.324
  },
  {
    "word": "now,",
    "start": 1.393,
    "end": 1.788
  },
  {
    "word": "in",
    "start": 1.997,
    "end": 2.136
  },
  {
    "word": "the",
    "start": 2.183,
    "end": 2.252
  },
  {
    "word": "way",
    "start": 2.31,
    "end": 2.461
  },
  {
    "word": "you",
    "start": 2.519,
    "end": 2.612
  },
  {
    "word": "see",
    "start": 2.705,
    "end": 2.902
  },
  {
    "word": "things",
    "start": 2.961,
    "end": 3.286
  },
  {
    "word": "in",
    "start": 3.344,
    "end": 3.413
  },
  {
    "word": "the",
    "start": 3.46,
    "end": 3.529
  },
  {
    "word": "dark",
    "start": 3.564,
    "end": 3.913
  },
  {
    "word": "when",
    "start": 3.982,
    "end": 4.145
  },
  {
    "word": "your",
    "start": 4.18,
    "end": 4.307
  },
  {
    "word": "eyes",
    "start": 4.377,
    "end": 4.714
  },
  {
    "word": "have",
    "start": 4.772,
    "end": 4.911
  },
  {
    "word": "stopped",
    "start": 4.946,
    "end": 5.317
  },
  {
    "word": "fighting",
    "start": 5.387,
    "end": 5.747
  },
  {
    "word": "the",
    "start": 5.805,
    "end": 5.875
  },
  {
    "word": "darkness",
    "start": 5.909,
    "end": 6.409
  },
  {
    "word": "and",
    "start": 6.455,
    "end": 6.548
  },
  {
    "word": "started",
    "start": 6.618,
    "end": 6.966
  },
  {
    "word": "working",
    "start": 7.024,
    "end": 7.361
  },
  {
    "word": "with",
    "start": 7.407,
    "end": 7.558
  },
  {
    "word": "it.",
    "start": 7.616,
    "end": 7.906
  },
  {
    "word": "It",
    "start": 8.51,
    "end": 8.661
  },
  {
    "word": "sat",
    "start": 8.731,
    "end": 9.056
  },
  {
    "word": "very",
    "start": 9.172,
    "end": 9.509
  },
  {
    "word": "still.",
    "start": 9.59,
    "end": 10.159
  },
  {
    "word": "It",
    "start": 10.762,
    "end": 10.913
  },
  {
    "word": "had",
    "start": 10.96,
    "end": 11.088
  },
  {
    "word": "a",
    "start": 11.134,
    "end": 11.157
  },
  {
    "word": "shape",
    "start": 11.238,
    "end": 11.622
  },
  {
    "word": "that",
    "start": 11.668,
    "end": 11.807
  },
  {
    "word": "was",
    "start": 11.854,
    "end": 11.981
  },
  {
    "word": "almost-Azi",
    "start": 12.063,
    "end": 13.108
  },
  {
    "word": "--",
    "start": 13.317,
    "end": 13.375
  },
  {
    "word": "the",
    "start": 13.584,
    "end": 13.688
  },
  {
    "word": "same",
    "start": 13.746,
    "end": 14.036
  },
  {
    "word": "hair,",
    "start": 14.094,
    "end": 14.617
  },
  {
    "word": "the",
    "start": 14.791,
    "end": 14.907
  },
  {
    "word": "same",
    "start": 14.965,
    "end": 15.255
  },
  {
    "word": "hands,",
    "start": 15.313,
    "end": 15.94
  },
  {
    "word": "the",
    "start": 16.115,
    "end": 16.231
  },
  {
    "word": "same",
    "start": 16.3,
    "end": 16.637
  },
  {
    "word": "small",
    "start": 16.695,
    "end": 17.125
  },
  {
    "word": "shoulders.",
    "start": 17.206,
    "end": 17.961
  },
  {
    "word": "But",
    "start": 18.402,
    "end": 18.564
  },
  {
    "word": "everything",
    "start": 18.622,
    "end": 19.005
  },
  {
    "word": "about",
    "start": 19.052,
    "end": 19.365
  },
  {
    "word": "it",
    "start": 19.412,
    "end": 19.493
  },
  {
    "word": "was",
    "start": 19.551,
    "end": 19.679
  },
  {
    "word": "dim,",
    "start": 19.76,
    "end": 20.317
  },
  {
    "word": "like",
    "start": 20.468,
    "end": 20.654
  },
  {
    "word": "a",
    "start": 20.689,
    "end": 20.712
  },
  {
    "word": "drawing",
    "start": 20.77,
    "end": 21.165
  },
  {
    "word": "of",
    "start": 21.223,
    "end": 21.293
  },
  {
    "word": "Azi",
    "start": 21.409,
    "end": 21.885
  },
  {
    "word": "made",
    "start": 22.001,
    "end": 22.256
  },
  {
    "word": "by",
    "start": 22.291,
    "end": 22.43
  },
  {
    "word": "someone",
    "start": 22.512,
    "end": 22.976
  },
  {
    "word": "who",
    "start": 23.011,
    "end": 23.127
  },
  {
    "word": "had",
    "start": 23.173,
    "end": 23.278
  },
  {
    "word": "only",
    "start": 23.336,
    "end": 23.557
  },
  {
    "word": "heard",
    "start": 23.626,
    "end": 23.847
  },
  {
    "word": "him",
    "start": 23.893,
    "end": 24.009
  },
  {
    "word": "described",
    "start": 24.067,
    "end": 24.752
  },
  {
    "word": "and",
    "start": 24.822,
    "end": 24.973
  },
  {
    "word": "never",
    "start": 25.066,
    "end": 25.345
  },
  {
    "word": "actually",
    "start": 25.426,
    "end": 25.925
  },
  {
    "word": "met",
    "start": 25.995,
    "end": 26.18
  },
  {
    "word": "him.",
    "start": 26.238,
    "end": 26.633
  },
  {
    "word": "Its",
    "start": 27.237,
    "end": 27.446
  },
  {
    "word": "arms",
    "start": 27.492,
    "end": 27.817
  },
  {
    "word": "were",
    "start": 27.875,
    "end": 28.015
  },
  {
    "word": "crossed.",
    "start": 28.061,
    "end": 28.758
  },
  {
    "word": "Its",
    "start": 29.083,
    "end": 29.315
  },
  {
    "word": "chin",
    "start": 29.385,
    "end": 29.687
  },
  {
    "word": "was",
    "start": 29.768,
    "end": 29.907
  },
  {
    "word": "pointed",
    "start": 29.988,
    "end": 30.372
  },
  {
    "word": "at",
    "start": 30.418,
    "end": 30.499
  },
  {
    "word": "the",
    "start": 30.534,
    "end": 30.604
  },
  {
    "word": "ceiling.",
    "start": 30.662,
    "end": 31.3
  },
  {
    "word": "It",
    "start": 31.811,
    "end": 31.951
  },
  {
    "word": "was",
    "start": 31.997,
    "end": 32.113
  },
  {
    "word": "wearing",
    "start": 32.171,
    "end": 32.508
  },
  {
    "word": "his",
    "start": 32.578,
    "end": 32.694
  },
  {
    "word": "expression",
    "start": 32.763,
    "end": 33.367
  },
  {
    "word": "from",
    "start": 33.437,
    "end": 33.599
  },
  {
    "word": "breakfast.",
    "start": 33.669,
    "end": 34.505
  }
]